graba/__init__.py
graba/main.py
graba-0.3.24.dist-info/LICENSE
graba-0.3.24.dist-info/METADATA
graba-0.3.24.dist-info/WHEEL
graba-0.3.24.dist-info/top_level.txt
graba-0.3.24.dist-info/RECORD
