Metadata-Version: 2.2
Name: graba
Version: 0.3.24
Summary: A library to generate random value for different concepts
Home-page: https://github.com/tatitati/graba
Author: Francisco Jose Albert Albusac
Author-email: francis.jaa@protonmail.com
Classifier: Programming Language :: Python :: 3
Classifier: License :: OSI Approved :: MIT License
Classifier: Operating System :: OS Independent
Requires-Python: >=3.6
License-File: LICENSE
Requires-Dist: python-dateutil>=2.8.2
Dynamic: author
Dynamic: author-email
Dynamic: classifier
Dynamic: description
Dynamic: description-content-type
Dynamic: home-page
Dynamic: requires-dist
Dynamic: requires-python
Dynamic: summary
